link/__init__.py
link/_logging_setup.py
link/_secrets.py
link/common.py
link/debuglink.py
link/exceptions.py
link/link.py
link/s3_writer.py
link/server.py
link/utils.py
link/configs/__init__.py
link/wrappers/__init__.py
link/wrappers/alexawrappers.py
link/wrappers/aolwrappers.py
link/wrappers/apiwrappers.py
link/wrappers/atlassianwrappers.py
link/wrappers/cassandrawrapper.py
link/wrappers/consolewrappers.py
link/wrappers/dbwrappers.py
link/wrappers/defaults.py
link/wrappers/elasticsearchwrappers.py
link/wrappers/forensiqimpactwrapper.py
link/wrappers/forensiqwrapper.py
link/wrappers/hivewrappers.py
link/wrappers/liverailwrappers.py
link/wrappers/logwrapper.py
link/wrappers/moatwrapper.py
link/wrappers/nosqlwrappers.py
link/wrappers/prestowrapper.py
link/wrappers/salesforcewrappers.py
link/wrappers/spotxwrappers.py
link/wrappers/springservewrappers.py
link/wrappers/yahoowrapper.py
link-2.1.4.dist-info/LICENSE
link-2.1.4.dist-info/METADATA
link-2.1.4.dist-info/WHEEL
link-2.1.4.dist-info/top_level.txt
link-2.1.4.dist-info/RECORD
